<?xml version="1.0" encoding="utf-8"?>
<annotation>
	<size>
		<width>2100</width>
		<height>1181</height>
		<depth>3</depth>
	</size>
	<object>
		<name>rectangle</name>
		<bndbox>
			<xmin>906.2583097033804</xmin>
			<ymin>317.54521655234083</ymin>
			<xmax>950.5359390994341</xmax>
			<ymax>357.07881422738876</ymax>
		</bndbox>
	</object>
	<object>
		<name>rectangle</name>
		<bndbox>
			<xmin>1004.3016319374993</xmin>
			<ymin>303.31312138932356</ymin>
			<xmax>1026.440446635526</xmax>
			<ymax>371.31090939040604</ymax>
		</bndbox>
	</object>
	<object>
		<name>rectangle</name>
		<bndbox>
			<xmin>1080.2061394735913</xmin>
			<ymin>319.1265604593427</ymin>
			<xmax>1121.3210810556413</xmax>
			<ymax>357.07881422738876</ymax>
		</bndbox>
	</object>
	<object>
		<name>rectangle</name>
		<bndbox>
			<xmin>882.5381510983516</xmin>
			<ymin>379.2176289254156</ymin>
			<xmax>985.3255050534763</xmax>
			<ymax>406.1004753444482</ymax>
		</bndbox>
	</object>
	<object>
		<name>rectangle</name>
		<bndbox>
			<xmin>1002.7202880304974</xmin>
			<ymin>382.38031673941947</ymin>
			<xmax>1029.60313444953</xmax>
			<ymax>402.9377875304444</ymax>
		</bndbox>
	</object>
	<object>
		<name>rectangle</name>
		<bndbox>
			<xmin>1056.4859808685626</xmin>
			<ymin>379.2176289254156</ymin>
			<xmax>1149.7852713816758</xmax>
			<ymax>406.1004753444482</ymax>
		</bndbox>
	</object>
	<object>
		<name>rectangle</name>
		<bndbox>
			<xmin>1080.2061394735913</xmin>
			<ymin>431.40197785647894</ymin>
			<xmax>1122.9024249626432</xmax>
			<ymax>477.26095115953456</ymax>
		</bndbox>
	</object>
	<object>
		<name>rectangle</name>
		<bndbox>
			<xmin>1001.1389441234954</xmin>
			<ymin>421.9139144144674</ymin>
			<xmax>1024.8591027285242</xmax>
			<ymax>482.0049828805403</ymax>
		</bndbox>
	</object>
	<object>
		<name>rectangle</name>
		<bndbox>
			<xmin>911.0023414243861</xmin>
			<ymin>429.820633949477</ymin>
			<xmax>953.6986269134379</xmax>
			<ymax>474.0982633455307</ymax>
		</bndbox>
	</object>
	<object>
		<name>rectangle</name>
		<bndbox>
			<xmin>711.7530091421445</xmin>
			<ymin>540.5147074396112</ymin>
			<xmax>763.9373580732077</xmax>
			<ymax>584.792336835665</ymax>
		</bndbox>
	</object>
	<object>
		<name>rectangle</name>
		<bndbox>
			<xmin>817.703050911273</xmin>
			<ymin>540.5147074396112</ymin>
			<xmax>866.7247120283324</xmax>
			<ymax>580.0483051146592</ymax>
		</bndbox>
	</object>
	<object>
		<name>circle</name>
		<bndbox>
			<xmin>768.6813897942135</xmin>
			<ymin>587.9550246496688</ymin>
			<xmax>806.6336435622595</xmax>
			<ymax>627.4886223247167</ymax>
		</bndbox>
	</object>
	<object>
		<name>rectangle</name>
		<bndbox>
			<xmin>716.4970408631502</xmin>
			<ymin>629.0699662317187</ymin>
			<xmax>760.774670259204</xmax>
			<ymax>671.7662517207705</ymax>
		</bndbox>
	</object>
	<object>
		<name>rectangle</name>
		<bndbox>
			<xmin>820.8657387252769</xmin>
			<ymin>633.8139979527244</ymin>
			<xmax>861.9806803073267</xmax>
			<ymax>674.9289395347743</ymax>
		</bndbox>
	</object>
	<object>
		<name>rectangle</name>
		<bndbox>
			<xmin>1171.9240860797026</xmin>
			<ymin>538.9333635326093</ymin>
			<xmax>1213.0390276617525</xmax>
			<ymax>581.6296490216611</ymax>
		</bndbox>
	</object>
	<object>
		<name>rectangle</name>
		<bndbox>
			<xmin>1279.455471755833</xmin>
			<ymin>537.3520196256075</ymin>
			<xmax>1314.2450377098753</xmax>
			<ymax>584.792336835665</ymax>
		</bndbox>
	</object>
	<object>
		<name>circle</name>
		<bndbox>
			<xmin>1227.2711228247697</xmin>
			<ymin>589.5363685566707</ymin>
			<xmax>1260.47934487181</xmax>
			<ymax>625.9072784177148</ymax>
		</bndbox>
	</object>
	<object>
		<name>rectangle</name>
		<bndbox>
			<xmin>1173.5054299867045</xmin>
			<ymin>632.2326540457225</ymin>
			<xmax>1214.6203715687543</xmax>
			<ymax>679.67297125578</ymax>
		</bndbox>
	</object>
	<object>
		<name>rectangle</name>
		<bndbox>
			<xmin>1276.2927839418292</xmin>
			<ymin>633.8139979527244</ymin>
			<xmax>1318.989069430881</xmax>
			<ymax>678.0916273487782</ymax>
		</bndbox>
	</object>
</annotation>
